README.md
setup.py
flask_star/__init__.py
flask_star/documentation.py
flask_star.egg-info/PKG-INFO
flask_star.egg-info/SOURCES.txt
flask_star.egg-info/dependency_links.txt
flask_star.egg-info/requires.txt
flask_star.egg-info/top_level.txt