Metadata-Version: 1.1
Name: flask-star
Version: 0.0.1
Summary: Porting apistar features to flask
Home-page: https://github.com/olirice/flask_star
Author: Oliver Rice
Author-email: oliver@oliverrice.com
License: BSD
Platform: UNKNOWN
Classifier: Development Status :: 4 - Beta
Classifier: Natural Language :: English
Classifier: Operating System :: OS Independent
Classifier: Programming Language :: Python
Classifier: Programming Language :: Python :: 3
Classifier: Programming Language :: Python :: 3.6
